odoo/addons/queue_job_batch/README.rst
odoo/addons/queue_job_batch/__init__.py
odoo/addons/queue_job_batch/__manifest__.py
odoo/addons/queue_job_batch/data/queue_job_channel_data.xml
odoo/addons/queue_job_batch/data/queue_job_function_data.xml
odoo/addons/queue_job_batch/i18n/es.po
odoo/addons/queue_job_batch/i18n/fr.po
odoo/addons/queue_job_batch/i18n/it.po
odoo/addons/queue_job_batch/i18n/queue_job_batch.pot
odoo/addons/queue_job_batch/models/__init__.py
odoo/addons/queue_job_batch/models/queue_job.py
odoo/addons/queue_job_batch/models/queue_job_batch.py
odoo/addons/queue_job_batch/readme/CONTRIBUTORS.rst
odoo/addons/queue_job_batch/readme/CREDITS.rst
odoo/addons/queue_job_batch/readme/DESCRIPTION.rst
odoo/addons/queue_job_batch/readme/USAGE.rst
odoo/addons/queue_job_batch/security/ir.model.access.csv
odoo/addons/queue_job_batch/security/security.xml
odoo/addons/queue_job_batch/static/description/icon.png
odoo/addons/queue_job_batch/static/description/icon.svg
odoo/addons/queue_job_batch/static/description/index.html
odoo/addons/queue_job_batch/static/src/js/systray.js
odoo/addons/queue_job_batch/static/src/scss/systray.scss
odoo/addons/queue_job_batch/static/src/xml/systray.xml
odoo/addons/queue_job_batch/tests/__init__.py
odoo/addons/queue_job_batch/tests/test_queue_job_batch.py
odoo/addons/queue_job_batch/views/assets_backend.xml
odoo/addons/queue_job_batch/views/queue_job_batch_views.xml
odoo/addons/queue_job_batch/views/queue_job_views.xml
odoo14_addon_queue_job_batch-14.0.1.0.2.dist-info/METADATA
odoo14_addon_queue_job_batch-14.0.1.0.2.dist-info/WHEEL
odoo14_addon_queue_job_batch-14.0.1.0.2.dist-info/top_level.txt
odoo14_addon_queue_job_batch-14.0.1.0.2.dist-info/RECORD
